qasem_parser/__init__.py
qasem_parser/argument_detection.py
qasem_parser/common_defs.py
qasem_parser/ling_utils.py
qasem_parser/predicate_detection.py
qasem_parser/qasem_parsing.py
qasem_parser/torch_utils.py
qasem_parser-1.1.16.dist-info/LICENSE
qasem_parser-1.1.16.dist-info/METADATA
qasem_parser-1.1.16.dist-info/WHEEL
qasem_parser-1.1.16.dist-info/top_level.txt
qasem_parser-1.1.16.dist-info/RECORD
