Metadata-Version: 2.1
Name: qasem_parser
Version: 1.1.16
Summary: QA based Semantics
Author-email: Paul Roit <plroit@gmail.com>
License: MIT License
Project-URL: Homepage, https://github.com/plroit/qasem_parser
Keywords: qasem,nlp,semantics
Classifier: License :: OSI Approved :: MIT License
Classifier: Programming Language :: Python
Classifier: Programming Language :: Python :: 3
Requires-Python: >=3.8
License-File: LICENSE
Requires-Dist: torch
Requires-Dist: transformers
Requires-Dist: spacy
Requires-Dist: qanom
Provides-Extra: dev
